netlify_dns_manage/__init__.py
netlify_dns_manage/driver.py
netlify_dns_manage/main.py
netlify_dns_manage/netlify_api.py
netlify_dns_manage/parser.py
netlify_dns_manage/utils.py
tests/__init__.py
tests/test_netlify_api.py
tests/test_parser.py
netlify_dns_manager-0.4.dist-info/LICENSE
netlify_dns_manager-0.4.dist-info/METADATA
netlify_dns_manager-0.4.dist-info/WHEEL
netlify_dns_manager-0.4.dist-info/entry_points.txt
netlify_dns_manager-0.4.dist-info/top_level.txt
netlify_dns_manager-0.4.dist-info/RECORD
