Metadata-Version: 2.1
Name: netlify-dns-manager
Version: 0.4
Summary: It provides a command line interface to manage DNS records of a domain hosted on Netlify.
Home-page: https://github.com/sumansaurabh/netlify-dns-manager
Classifier: Programming Language :: Python :: 3
Classifier: License :: OSI Approved :: MIT License
Classifier: Operating System :: OS Independent
Requires-Python: >=3.6
License-File: LICENSE
Requires-Dist: requests
Requires-Dist: dnspython
Requires-Dist: zonefile-parser
